CHANGES.rst
CONTRIBUTORS.rst
MANIFEST.in
README.rst
setup.cfg
setup.py
docs/LICENSE.GPL
docs/LICENSE.txt
src/collective/__init__.py
src/collective.liveblog.egg-info/PKG-INFO
src/collective.liveblog.egg-info/SOURCES.txt
src/collective.liveblog.egg-info/dependency_links.txt
src/collective.liveblog.egg-info/entry_points.txt
src/collective.liveblog.egg-info/namespace_packages.txt
src/collective.liveblog.egg-info/not-zip-safe
src/collective.liveblog.egg-info/requires.txt
src/collective.liveblog.egg-info/top_level.txt
src/collective/liveblog/__init__.py
src/collective/liveblog/adapters.py
src/collective/liveblog/config.py
src/collective/liveblog/configure.zcml
src/collective/liveblog/content.py
src/collective/liveblog/interfaces.py
src/collective/liveblog/logger.py
src/collective/liveblog/profiles.zcml
src/collective/liveblog/setuphandlers.py
src/collective/liveblog/testing.py
src/collective/liveblog/testing.zcml
src/collective/liveblog/browser/__init__.py
src/collective/liveblog/browser/base.py
src/collective/liveblog/browser/configure.zcml
src/collective/liveblog/browser/header.py
src/collective/liveblog/browser/microupdates.py
src/collective/liveblog/browser/recent_updates.py
src/collective/liveblog/browser/update.py
src/collective/liveblog/browser/view.py
src/collective/liveblog/browser/templates/edit.pt
src/collective/liveblog/browser/templates/header.pt
src/collective/liveblog/browser/templates/microupdate.pt
src/collective/liveblog/browser/templates/recent_updates.pt
src/collective/liveblog/browser/templates/update.pt
src/collective/liveblog/browser/templates/view.pt
src/collective/liveblog/caching/__init__.py
src/collective/liveblog/caching/configure.zcml
src/collective/liveblog/caching/purge.py
src/collective/liveblog/locales/collective.liveblog.pot
src/collective/liveblog/locales/manual.pot
src/collective/liveblog/locales/plone.pot
src/collective/liveblog/locales/es/LC_MESSAGES/collective.liveblog.po
src/collective/liveblog/locales/es/LC_MESSAGES/plone.po
src/collective/liveblog/locales/pt_BR/LC_MESSAGES/collective.liveblog.po
src/collective/liveblog/locales/pt_BR/LC_MESSAGES/plone.po
src/collective/liveblog/profiles/default/browserlayer.xml
src/collective/liveblog/profiles/default/cssregistry.xml
src/collective/liveblog/profiles/default/metadata.xml
src/collective/liveblog/profiles/default/rolemap.xml
