Metadata-Version: 1.1
Name: collective.liveblog
Version: 1.2b1
Summary: A liveblogging solution for Plone.
Home-page: https://github.com/collective/collective.liveblog
Author: Simples Consutoria
Author-email: produtos@simplesconsultoria.com.br
License: UNKNOWN
Keywords: plone liveblogging dexterity
Platform: UNKNOWN
Classifier: Development Status :: 4 - Beta
Classifier: Environment :: Web Environment
Classifier: Framework :: Plone
Classifier: Framework :: Plone :: 4.3
Classifier: Framework :: Plone :: 5.0
Classifier: Intended Audience :: System Administrators
Classifier: License :: OSI Approved :: GNU General Public License v2 (GPLv2)
Classifier: Operating System :: OS Independent
Classifier: Programming Language :: JavaScript
Classifier: Programming Language :: Python
Classifier: Programming Language :: Python :: 2.7
Classifier: Topic :: Office/Business :: News/Diary
Classifier: Topic :: Software Development :: Libraries :: Python Modules
